[
  {
    "bolusinsulin": 0, 
    "bolusiob": 0, 
    "lastTemp": {
      "date": 1561286418000, 
      "timestamp": "2019-06-23T03:40:18-07:00", 
      "rate": 0.5, 
      "started_at": "2019-06-23T10:40:18.000Z", 
      "duration": 30
    }, 
    "netbasalinsulin": -0.85, 
    "basaliob": -0.447, 
    "lastBolusTime": 0, 
    "time": "2019-06-23T10:45:20.000Z", 
    "activity": -0.0034, 
    "iobWithZeroTemp": {
      "bolusinsulin": 0, 
      "bolusiob": 0, 
      "netbasalinsulin": -0.95, 
      "basaliob": -0.451, 
      "time": "2019-06-23T10:45:20.000Z", 
      "activity": -0.0035, 
      "iob": -0.451
    }, 
    "iob": -0.447
  }, 
  {
    "bolusinsulin": 0, 
    "bolusiob": 0, 
    "netbasalinsulin": -0.85, 
    "basaliob": -0.43, 
    "time": "2019-06-23T10:50:20.000Z", 
    "activity": -0.0034, 
    "iobWithZeroTemp": {
      "bolusinsulin": 0, 
      "bolusiob": 0, 
      "netbasalinsulin": -0.9, 
      "basaliob": -0.432, 
      "time": "2019-06-23T10:50:20.000Z", 
      "activity": -0.0035, 
      "iob": -0.432
    }, 
    "iob": -0.43
  }, 
  {
    "bolusinsulin": 0, 
    "bolusiob": 0, 
    "netbasalinsulin": -0.9, 
    "basaliob": -0.463, 
    "time": "2019-06-23T10:55:20.000Z", 
    "activity": -0.0035, 
    "iobWithZeroTemp": {
      "bolusinsulin": 0, 
      "bolusiob": 0, 
      "netbasalinsulin": -0.9, 
      "basaliob": -0.463, 
      "time": "2019-06-23T10:55:20.000Z", 
      "activity": -0.0035, 
      "iob": -0.463
    }, 
    "iob": -0.463
  }, 
  {
    "bolusinsulin": 0, 
    "bolusiob": 0, 
    "netbasalinsulin": -0.9, 
    "basaliob": -0.445, 
    "time": "2019-06-23T11:00:20.000Z", 
    "activity": -0.0036, 
    "iobWithZeroTemp": {
      "bolusinsulin": 0, 
      "bolusiob": 0, 
      "netbasalinsulin": -0.9, 
      "basaliob": -0.445, 
      "time": "2019-06-23T11:00:20.000Z", 
      "activity": -0.0036, 
      "iob": -0.445
    }, 
    "iob": -0.445
  }, 
  {
    "bolusinsulin": 0, 
    "bolusiob": 0, 
    "netbasalinsulin": -0.9, 
    "basaliob": -0.427, 
    "time": "2019-06-23T11:05:20.000Z", 
    "activity": -0.0036, 
    "iobWithZeroTemp": {
      "bolusinsulin": 0, 
      "bolusiob": 0, 
      "netbasalinsulin": -0.9, 
      "basaliob": -0.427, 
      "time": "2019-06-23T11:05:20.000Z", 
      "activity": -0.0036, 
      "iob": -0.427
    }, 
    "iob": -0.427
  }, 
  {
    "bolusinsulin": 0, 
    "bolusiob": 0, 
    "netbasalinsulin": -0.9, 
    "basaliob": -0.409, 
    "time": "2019-06-23T11:10:20.000Z", 
    "activity": -0.0036, 
    "iobWithZeroTemp": {
      "bolusinsulin": 0, 
      "bolusiob": 0, 
      "netbasalinsulin": -0.9, 
      "basaliob": -0.409, 
      "time": "2019-06-23T11:10:20.000Z", 
      "activity": -0.0036, 
      "iob": -0.409
    }, 
    "iob": -0.409
  }, 
  {
    "bolusinsulin": 0, 
    "bolusiob": 0, 
    "netbasalinsulin": -0.85, 
    "basaliob": -0.39, 
    "time": "2019-06-23T11:15:20.000Z", 
    "activity": -0.0036, 
    "iobWithZeroTemp": {
      "bolusinsulin": 0, 
      "bolusiob": 0, 
      "netbasalinsulin": -0.85, 
      "basaliob": -0.39, 
      "time": "2019-06-23T11:15:20.000Z", 
      "activity": -0.0036, 
      "iob": -0.39
    }, 
    "iob": -0.39
  }, 
  {
    "bolusinsulin": 0, 
    "bolusiob": 0, 
    "netbasalinsulin": -0.8, 
    "basaliob": -0.37, 
    "time": "2019-06-23T11:20:20.000Z", 
    "activity": -0.0035, 
    "iobWithZeroTemp": {
      "bolusinsulin": 0, 
      "bolusiob": 0, 
      "netbasalinsulin": -0.8, 
      "basaliob": -0.37, 
      "time": "2019-06-23T11:20:20.000Z", 
      "activity": -0.0035, 
      "iob": -0.37
    }, 
    "iob": -0.37
  }, 
  {
    "bolusinsulin": 0, 
    "bolusiob": 0, 
    "netbasalinsulin": -0.8, 
    "basaliob": -0.353, 
    "time": "2019-06-23T11:25:20.000Z", 
    "activity": -0.0035, 
    "iobWithZeroTemp": {
      "bolusinsulin": 0, 
      "bolusiob": 0, 
      "netbasalinsulin": -0.8, 
      "basaliob": -0.353, 
      "time": "2019-06-23T11:25:20.000Z", 
      "activity": -0.0035, 
      "iob": -0.353
    }, 
    "iob": -0.353
  }, 
  {
    "bolusinsulin": 0, 
    "bolusiob": 0, 
    "netbasalinsulin": -0.75, 
    "basaliob": -0.334, 
    "time": "2019-06-23T11:30:20.000Z", 
    "activity": -0.0034, 
    "iobWithZeroTemp": {
      "bolusinsulin": 0, 
      "bolusiob": 0, 
      "netbasalinsulin": -0.75, 
      "basaliob": -0.334, 
      "time": "2019-06-23T11:30:20.000Z", 
      "activity": -0.0034, 
      "iob": -0.334
    }, 
    "iob": -0.334
  }, 
  {
    "bolusinsulin": 0, 
    "bolusiob": 0, 
    "netbasalinsulin": -0.75, 
    "basaliob": -0.317, 
    "time": "2019-06-23T11:35:20.000Z", 
    "activity": -0.0033, 
    "iobWithZeroTemp": {
      "bolusinsulin": 0, 
      "bolusiob": 0, 
      "netbasalinsulin": -0.75, 
      "basaliob": -0.317, 
      "time": "2019-06-23T11:35:20.000Z", 
      "activity": -0.0033, 
      "iob": -0.317
    }, 
    "iob": -0.317
  }, 
  {
    "bolusinsulin": 0, 
    "bolusiob": 0, 
    "netbasalinsulin": -0.75, 
    "basaliob": -0.301, 
    "time": "2019-06-23T11:40:20.000Z", 
    "activity": -0.0033, 
    "iobWithZeroTemp": {
      "bolusinsulin": 0, 
      "bolusiob": 0, 
      "netbasalinsulin": -0.75, 
      "basaliob": -0.301, 
      "time": "2019-06-23T11:40:20.000Z", 
      "activity": -0.0033, 
      "iob": -0.301
    }, 
    "iob": -0.301
  }, 
  {
    "bolusinsulin": 0, 
    "bolusiob": 0, 
    "netbasalinsulin": -0.7, 
    "basaliob": -0.283, 
    "time": "2019-06-23T11:45:20.000Z", 
    "activity": -0.0032, 
    "iobWithZeroTemp": {
      "bolusinsulin": 0, 
      "bolusiob": 0, 
      "netbasalinsulin": -0.7, 
      "basaliob": -0.283, 
      "time": "2019-06-23T11:45:20.000Z", 
      "activity": -0.0032, 
      "iob": -0.283
    }, 
    "iob": -0.283
  }, 
  {
    "bolusinsulin": 0, 
    "bolusiob": 0, 
    "netbasalinsulin": -0.7, 
    "basaliob": -0.267, 
    "time": "2019-06-23T11:50:20.000Z", 
    "activity": -0.0031, 
    "iobWithZeroTemp": {
      "bolusinsulin": 0, 
      "bolusiob": 0, 
      "netbasalinsulin": -0.7, 
      "basaliob": -0.267, 
      "time": "2019-06-23T11:50:20.000Z", 
      "activity": -0.0031, 
      "iob": -0.267
    }, 
    "iob": -0.267
  }, 
  {
    "bolusinsulin": 0, 
    "bolusiob": 0, 
    "netbasalinsulin": -0.7, 
    "basaliob": -0.252, 
    "time": "2019-06-23T11:55:20.000Z", 
    "activity": -0.003, 
    "iobWithZeroTemp": {
      "bolusinsulin": 0, 
      "bolusiob": 0, 
      "netbasalinsulin": -0.7, 
      "basaliob": -0.252, 
      "time": "2019-06-23T11:55:20.000Z", 
      "activity": -0.003, 
      "iob": -0.252
    }, 
    "iob": -0.252
  }, 
  {
    "bolusinsulin": 0, 
    "bolusiob": 0, 
    "netbasalinsulin": -0.65, 
    "basaliob": -0.235, 
    "time": "2019-06-23T12:00:20.000Z", 
    "activity": -0.0029, 
    "iobWithZeroTemp": {
      "bolusinsulin": 0, 
      "bolusiob": 0, 
      "netbasalinsulin": -0.65, 
      "basaliob": -0.235, 
      "time": "2019-06-23T12:00:20.000Z", 
      "activity": -0.0029, 
      "iob": -0.235
    }, 
    "iob": -0.235
  }, 
  {
    "bolusinsulin": 0, 
    "bolusiob": 0, 
    "netbasalinsulin": -0.65, 
    "basaliob": -0.221, 
    "time": "2019-06-23T12:05:20.000Z", 
    "activity": -0.0028, 
    "iobWithZeroTemp": {
      "bolusinsulin": 0, 
      "bolusiob": 0, 
      "netbasalinsulin": -0.65, 
      "basaliob": -0.221, 
      "time": "2019-06-23T12:05:20.000Z", 
      "activity": -0.0028, 
      "iob": -0.221
    }, 
    "iob": -0.221
  }, 
  {
    "bolusinsulin": 0, 
    "bolusiob": 0, 
    "netbasalinsulin": -0.65, 
    "basaliob": -0.207, 
    "time": "2019-06-23T12:10:20.000Z", 
    "activity": -0.0027, 
    "iobWithZeroTemp": {
      "bolusinsulin": 0, 
      "bolusiob": 0, 
      "netbasalinsulin": -0.65, 
      "basaliob": -0.207, 
      "time": "2019-06-23T12:10:20.000Z", 
      "activity": -0.0027, 
      "iob": -0.207
    }, 
    "iob": -0.207
  }, 
  {
    "bolusinsulin": 0, 
    "bolusiob": 0, 
    "netbasalinsulin": -0.6, 
    "basaliob": -0.193, 
    "time": "2019-06-23T12:15:20.000Z", 
    "activity": -0.0026, 
    "iobWithZeroTemp": {
      "bolusinsulin": 0, 
      "bolusiob": 0, 
      "netbasalinsulin": -0.6, 
      "basaliob": -0.193, 
      "time": "2019-06-23T12:15:20.000Z", 
      "activity": -0.0026, 
      "iob": -0.193
    }, 
    "iob": -0.193
  }, 
  {
    "bolusinsulin": 0, 
    "bolusiob": 0, 
    "netbasalinsulin": -0.6, 
    "basaliob": -0.18, 
    "time": "2019-06-23T12:20:20.000Z", 
    "activity": -0.0025, 
    "iobWithZeroTemp": {
      "bolusinsulin": 0, 
      "bolusiob": 0, 
      "netbasalinsulin": -0.6, 
      "basaliob": -0.18, 
      "time": "2019-06-23T12:20:20.000Z", 
      "activity": -0.0025, 
      "iob": -0.18
    }, 
    "iob": -0.18
  }, 
  {
    "bolusinsulin": 0, 
    "bolusiob": 0, 
    "netbasalinsulin": -0.6, 
    "basaliob": -0.168, 
    "time": "2019-06-23T12:25:20.000Z", 
    "activity": -0.0024, 
    "iobWithZeroTemp": {
      "bolusinsulin": 0, 
      "bolusiob": 0, 
      "netbasalinsulin": -0.6, 
      "basaliob": -0.168, 
      "time": "2019-06-23T12:25:20.000Z", 
      "activity": -0.0024, 
      "iob": -0.168
    }, 
    "iob": -0.168
  }, 
  {
    "bolusinsulin": 0, 
    "bolusiob": 0, 
    "netbasalinsulin": -0.55, 
    "basaliob": -0.155, 
    "time": "2019-06-23T12:30:20.000Z", 
    "activity": -0.0022, 
    "iobWithZeroTemp": {
      "bolusinsulin": 0, 
      "bolusiob": 0, 
      "netbasalinsulin": -0.55, 
      "basaliob": -0.155, 
      "time": "2019-06-23T12:30:20.000Z", 
      "activity": -0.0022, 
      "iob": -0.155
    }, 
    "iob": -0.155
  }, 
  {
    "bolusinsulin": 0, 
    "bolusiob": 0, 
    "netbasalinsulin": -0.55, 
    "basaliob": -0.144, 
    "time": "2019-06-23T12:35:20.000Z", 
    "activity": -0.0021, 
    "iobWithZeroTemp": {
      "bolusinsulin": 0, 
      "bolusiob": 0, 
      "netbasalinsulin": -0.55, 
      "basaliob": -0.144, 
      "time": "2019-06-23T12:35:20.000Z", 
      "activity": -0.0021, 
      "iob": -0.144
    }, 
    "iob": -0.144
  }, 
  {
    "bolusinsulin": 0, 
    "bolusiob": 0, 
    "netbasalinsulin": -0.55, 
    "basaliob": -0.134, 
    "time": "2019-06-23T12:40:20.000Z", 
    "activity": -0.002, 
    "iobWithZeroTemp": {
      "bolusinsulin": 0, 
      "bolusiob": 0, 
      "netbasalinsulin": -0.55, 
      "basaliob": -0.134, 
      "time": "2019-06-23T12:40:20.000Z", 
      "activity": -0.002, 
      "iob": -0.134
    }, 
    "iob": -0.134
  }, 
  {
    "bolusinsulin": 0, 
    "bolusiob": 0, 
    "netbasalinsulin": -0.5, 
    "basaliob": -0.122, 
    "time": "2019-06-23T12:45:20.000Z", 
    "activity": -0.0019, 
    "iobWithZeroTemp": {
      "bolusinsulin": 0, 
      "bolusiob": 0, 
      "netbasalinsulin": -0.5, 
      "basaliob": -0.122, 
      "time": "2019-06-23T12:45:20.000Z", 
      "activity": -0.0019, 
      "iob": -0.122
    }, 
    "iob": -0.122
  }, 
  {
    "bolusinsulin": 0, 
    "bolusiob": 0, 
    "netbasalinsulin": -0.5, 
    "basaliob": -0.113, 
    "time": "2019-06-23T12:50:20.000Z", 
    "activity": -0.0018, 
    "iobWithZeroTemp": {
      "bolusinsulin": 0, 
      "bolusiob": 0, 
      "netbasalinsulin": -0.5, 
      "basaliob": -0.113, 
      "time": "2019-06-23T12:50:20.000Z", 
      "activity": -0.0018, 
      "iob": -0.113
    }, 
    "iob": -0.113
  }, 
  {
    "bolusinsulin": 0, 
    "bolusiob": 0, 
    "netbasalinsulin": -0.5, 
    "basaliob": -0.104, 
    "time": "2019-06-23T12:55:20.000Z", 
    "activity": -0.0017, 
    "iobWithZeroTemp": {
      "bolusinsulin": 0, 
      "bolusiob": 0, 
      "netbasalinsulin": -0.5, 
      "basaliob": -0.104, 
      "time": "2019-06-23T12:55:20.000Z", 
      "activity": -0.0017, 
      "iob": -0.104
    }, 
    "iob": -0.104
  }, 
  {
    "bolusinsulin": 0, 
    "bolusiob": 0, 
    "netbasalinsulin": -0.45, 
    "basaliob": -0.094, 
    "time": "2019-06-23T13:00:20.000Z", 
    "activity": -0.0016, 
    "iobWithZeroTemp": {
      "bolusinsulin": 0, 
      "bolusiob": 0, 
      "netbasalinsulin": -0.45, 
      "basaliob": -0.094, 
      "time": "2019-06-23T13:00:20.000Z", 
      "activity": -0.0016, 
      "iob": -0.094
    }, 
    "iob": -0.094
  }, 
  {
    "bolusinsulin": 0, 
    "bolusiob": 0, 
    "netbasalinsulin": -0.45, 
    "basaliob": -0.086, 
    "time": "2019-06-23T13:05:20.000Z", 
    "activity": -0.0015, 
    "iobWithZeroTemp": {
      "bolusinsulin": 0, 
      "bolusiob": 0, 
      "netbasalinsulin": -0.45, 
      "basaliob": -0.086, 
      "time": "2019-06-23T13:05:20.000Z", 
      "activity": -0.0015, 
      "iob": -0.086
    }, 
    "iob": -0.086
  }, 
  {
    "bolusinsulin": 0, 
    "bolusiob": 0, 
    "netbasalinsulin": -0.45, 
    "basaliob": -0.079, 
    "time": "2019-06-23T13:10:20.000Z", 
    "activity": -0.0014, 
    "iobWithZeroTemp": {
      "bolusinsulin": 0, 
      "bolusiob": 0, 
      "netbasalinsulin": -0.45, 
      "basaliob": -0.079, 
      "time": "2019-06-23T13:10:20.000Z", 
      "activity": -0.0014, 
      "iob": -0.079
    }, 
    "iob": -0.079
  }, 
  {
    "bolusinsulin": 0, 
    "bolusiob": 0, 
    "netbasalinsulin": -0.45, 
    "basaliob": -0.072, 
    "time": "2019-06-23T13:15:20.000Z", 
    "activity": -0.0013, 
    "iobWithZeroTemp": {
      "bolusinsulin": 0, 
      "bolusiob": 0, 
      "netbasalinsulin": -0.45, 
      "basaliob": -0.072, 
      "time": "2019-06-23T13:15:20.000Z", 
      "activity": -0.0013, 
      "iob": -0.072
    }, 
    "iob": -0.072
  }, 
  {
    "bolusinsulin": 0, 
    "bolusiob": 0, 
    "netbasalinsulin": -0.4, 
    "basaliob": -0.064, 
    "time": "2019-06-23T13:20:20.000Z", 
    "activity": -0.0012, 
    "iobWithZeroTemp": {
      "bolusinsulin": 0, 
      "bolusiob": 0, 
      "netbasalinsulin": -0.4, 
      "basaliob": -0.064, 
      "time": "2019-06-23T13:20:20.000Z", 
      "activity": -0.0012, 
      "iob": -0.064
    }, 
    "iob": -0.064
  }, 
  {
    "bolusinsulin": 0, 
    "bolusiob": 0, 
    "netbasalinsulin": -0.4, 
    "basaliob": -0.058, 
    "time": "2019-06-23T13:25:20.000Z", 
    "activity": -0.0011, 
    "iobWithZeroTemp": {
      "bolusinsulin": 0, 
      "bolusiob": 0, 
      "netbasalinsulin": -0.4, 
      "basaliob": -0.058, 
      "time": "2019-06-23T13:25:20.000Z", 
      "activity": -0.0011, 
      "iob": -0.058
    }, 
    "iob": -0.058
  }, 
  {
    "bolusinsulin": 0, 
    "bolusiob": 0, 
    "netbasalinsulin": -0.35, 
    "basaliob": -0.051, 
    "time": "2019-06-23T13:30:20.000Z", 
    "activity": -0.001, 
    "iobWithZeroTemp": {
      "bolusinsulin": 0, 
      "bolusiob": 0, 
      "netbasalinsulin": -0.35, 
      "basaliob": -0.051, 
      "time": "2019-06-23T13:30:20.000Z", 
      "activity": -0.001, 
      "iob": -0.051
    }, 
    "iob": -0.051
  }, 
  {
    "bolusinsulin": 0, 
    "bolusiob": 0, 
    "netbasalinsulin": -0.35, 
    "basaliob": -0.046, 
    "time": "2019-06-23T13:35:20.000Z", 
    "activity": -0.0009, 
    "iobWithZeroTemp": {
      "bolusinsulin": 0, 
      "bolusiob": 0, 
      "netbasalinsulin": -0.35, 
      "basaliob": -0.046, 
      "time": "2019-06-23T13:35:20.000Z", 
      "activity": -0.0009, 
      "iob": -0.046
    }, 
    "iob": -0.046
  }, 
  {
    "bolusinsulin": 0, 
    "bolusiob": 0, 
    "netbasalinsulin": -0.35, 
    "basaliob": -0.042, 
    "time": "2019-06-23T13:40:20.000Z", 
    "activity": -0.0009, 
    "iobWithZeroTemp": {
      "bolusinsulin": 0, 
      "bolusiob": 0, 
      "netbasalinsulin": -0.35, 
      "basaliob": -0.042, 
      "time": "2019-06-23T13:40:20.000Z", 
      "activity": -0.0009, 
      "iob": -0.042
    }, 
    "iob": -0.042
  }, 
  {
    "bolusinsulin": 0, 
    "bolusiob": 0, 
    "netbasalinsulin": -0.3, 
    "basaliob": -0.036, 
    "time": "2019-06-23T13:45:20.000Z", 
    "activity": -0.0008, 
    "iobWithZeroTemp": {
      "bolusinsulin": 0, 
      "bolusiob": 0, 
      "netbasalinsulin": -0.3, 
      "basaliob": -0.036, 
      "time": "2019-06-23T13:45:20.000Z", 
      "activity": -0.0008, 
      "iob": -0.036
    }, 
    "iob": -0.036
  }, 
  {
    "bolusinsulin": 0, 
    "bolusiob": 0, 
    "netbasalinsulin": -0.3, 
    "basaliob": -0.032, 
    "time": "2019-06-23T13:50:20.000Z", 
    "activity": -0.0007, 
    "iobWithZeroTemp": {
      "bolusinsulin": 0, 
      "bolusiob": 0, 
      "netbasalinsulin": -0.3, 
      "basaliob": -0.032, 
      "time": "2019-06-23T13:50:20.000Z", 
      "activity": -0.0007, 
      "iob": -0.032
    }, 
    "iob": -0.032
  }, 
  {
    "bolusinsulin": 0, 
    "bolusiob": 0, 
    "netbasalinsulin": -0.3, 
    "basaliob": -0.028, 
    "time": "2019-06-23T13:55:20.000Z", 
    "activity": -0.0007, 
    "iobWithZeroTemp": {
      "bolusinsulin": 0, 
      "bolusiob": 0, 
      "netbasalinsulin": -0.3, 
      "basaliob": -0.028, 
      "time": "2019-06-23T13:55:20.000Z", 
      "activity": -0.0007, 
      "iob": -0.028
    }, 
    "iob": -0.028
  }, 
  {
    "bolusinsulin": 0, 
    "bolusiob": 0, 
    "netbasalinsulin": -0.3, 
    "basaliob": -0.025, 
    "time": "2019-06-23T14:00:20.000Z", 
    "activity": -0.0006, 
    "iobWithZeroTemp": {
      "bolusinsulin": 0, 
      "bolusiob": 0, 
      "netbasalinsulin": -0.3, 
      "basaliob": -0.025, 
      "time": "2019-06-23T14:00:20.000Z", 
      "activity": -0.0006, 
      "iob": -0.025
    }, 
    "iob": -0.025
  }, 
  {
    "bolusinsulin": 0, 
    "bolusiob": 0, 
    "netbasalinsulin": -0.25, 
    "basaliob": -0.021, 
    "time": "2019-06-23T14:05:20.000Z", 
    "activity": -0.0005, 
    "iobWithZeroTemp": {
      "bolusinsulin": 0, 
      "bolusiob": 0, 
      "netbasalinsulin": -0.25, 
      "basaliob": -0.021, 
      "time": "2019-06-23T14:05:20.000Z", 
      "activity": -0.0005, 
      "iob": -0.021
    }, 
    "iob": -0.021
  }, 
  {
    "bolusinsulin": 0, 
    "bolusiob": 0, 
    "netbasalinsulin": -0.25, 
    "basaliob": -0.018, 
    "time": "2019-06-23T14:10:20.000Z", 
    "activity": -0.0005, 
    "iobWithZeroTemp": {
      "bolusinsulin": 0, 
      "bolusiob": 0, 
      "netbasalinsulin": -0.25, 
      "basaliob": -0.018, 
      "time": "2019-06-23T14:10:20.000Z", 
      "activity": -0.0005, 
      "iob": -0.018
    }, 
    "iob": -0.018
  }, 
  {
    "bolusinsulin": 0, 
    "bolusiob": 0, 
    "netbasalinsulin": -0.2, 
    "basaliob": -0.014, 
    "time": "2019-06-23T14:15:20.000Z", 
    "activity": -0.0004, 
    "iobWithZeroTemp": {
      "bolusinsulin": 0, 
      "bolusiob": 0, 
      "netbasalinsulin": -0.2, 
      "basaliob": -0.014, 
      "time": "2019-06-23T14:15:20.000Z", 
      "activity": -0.0004, 
      "iob": -0.014
    }, 
    "iob": -0.014
  }, 
  {
    "bolusinsulin": 0, 
    "bolusiob": 0, 
    "netbasalinsulin": -0.2, 
    "basaliob": -0.012, 
    "time": "2019-06-23T14:20:20.000Z", 
    "activity": -0.0003, 
    "iobWithZeroTemp": {
      "bolusinsulin": 0, 
      "bolusiob": 0, 
      "netbasalinsulin": -0.2, 
      "basaliob": -0.012, 
      "time": "2019-06-23T14:20:20.000Z", 
      "activity": -0.0003, 
      "iob": -0.012
    }, 
    "iob": -0.012
  }, 
  {
    "bolusinsulin": 0, 
    "bolusiob": 0, 
    "netbasalinsulin": -0.15, 
    "basaliob": -0.009, 
    "time": "2019-06-23T14:25:20.000Z", 
    "activity": -0.0003, 
    "iobWithZeroTemp": {
      "bolusinsulin": 0, 
      "bolusiob": 0, 
      "netbasalinsulin": -0.15, 
      "basaliob": -0.009, 
      "time": "2019-06-23T14:25:20.000Z", 
      "activity": -0.0003, 
      "iob": -0.009
    }, 
    "iob": -0.009
  }, 
  {
    "bolusinsulin": 0, 
    "bolusiob": 0, 
    "netbasalinsulin": -0.15, 
    "basaliob": -0.008, 
    "time": "2019-06-23T14:30:20.000Z", 
    "activity": -0.0002, 
    "iobWithZeroTemp": {
      "bolusinsulin": 0, 
      "bolusiob": 0, 
      "netbasalinsulin": -0.15, 
      "basaliob": -0.008, 
      "time": "2019-06-23T14:30:20.000Z", 
      "activity": -0.0002, 
      "iob": -0.008
    }, 
    "iob": -0.008
  }, 
  {
    "bolusinsulin": 0, 
    "bolusiob": 0, 
    "netbasalinsulin": -0.1, 
    "basaliob": -0.005, 
    "time": "2019-06-23T14:35:20.000Z", 
    "activity": -0.0002, 
    "iobWithZeroTemp": {
      "bolusinsulin": 0, 
      "bolusiob": 0, 
      "netbasalinsulin": -0.1, 
      "basaliob": -0.005, 
      "time": "2019-06-23T14:35:20.000Z", 
      "activity": -0.0002, 
      "iob": -0.005
    }, 
    "iob": -0.005
  }, 
  {
    "bolusinsulin": 0, 
    "bolusiob": 0, 
    "netbasalinsulin": -0.05, 
    "basaliob": -0.003, 
    "time": "2019-06-23T14:40:20.000Z", 
    "activity": -0.0001, 
    "iobWithZeroTemp": {
      "bolusinsulin": 0, 
      "bolusiob": 0, 
      "netbasalinsulin": -0.05, 
      "basaliob": -0.003, 
      "time": "2019-06-23T14:40:20.000Z", 
      "activity": -0.0001, 
      "iob": -0.003
    }, 
    "iob": -0.003
  }
]